mf/__init__.py
microformats-0.5.1.dist-info/LICENSE.mf2util
microformats-0.5.1.dist-info/METADATA
microformats-0.5.1.dist-info/entry_points.txt
microformats-0.5.1.dist-info/WHEEL
microformats-0.5.1.dist-info/RECORD
