Metadata-Version: 2.1
Name: microformats
Version: 0.5.1
Summary: tools for microformats production, consumption and analysis
Home-page: https://ragt.ag/code/projects/python-microformats
License: BSD-3-Clause
Keywords: IndieWeb,microformats
Author: Angelo Gladding
Author-email: angelo@ragt.ag
Requires-Python: >=3.10,<3.11
Classifier: License :: OSI Approved :: BSD License
Classifier: Programming Language :: Python :: 3
Classifier: Programming Language :: Python :: 3.10
Requires-Dist: beautifulsoup4 (>=4.11.2,<5.0.0)
Requires-Dist: easyuri (>=0.1.2)
Requires-Dist: mf2py (>=2.0.1,<3.0.0)
Requires-Dist: txtint (>=0.1.2)
